ebi_mpl/__init__.py
ebi_mpl/lab.mplstyle
ebi_mpl-0.1.0.dist-info/METADATA
ebi_mpl-0.1.0.dist-info/WHEEL
ebi_mpl-0.1.0.dist-info/top_level.txt
ebi_mpl-0.1.0.dist-info/RECORD
