Metadata-Version: 2.4
Name: ebi_mpl
Version: 0.1.0
Summary: ebi's style for Matplotlib
Author-email: Yusuke Ebihara <ebihara@ntech.t.u-tokyo.ac.jp>
License: MIT
Project-URL: Homepage, https://github.com/ebiyu/ebi_mpl
Classifier: Programming Language :: Python :: 3
Classifier: License :: OSI Approved :: MIT License
Classifier: Operating System :: OS Independent
Requires-Python: >=3.7
Requires-Dist: matplotlib
